dotsecrets/__init__.py
dotsecrets/clean.py
dotsecrets/compat.py
dotsecrets/init.py
dotsecrets/main.py
dotsecrets/metadata.py
dotsecrets/params.py
dotsecrets/smudge.py
dotsecrets/stow.py
dotsecrets/test.py
dotsecrets/textsub.py
dotsecrets/utils.py
dotsecrets-0.4.1.dist-info/METADATA
dotsecrets-0.4.1.dist-info/WHEEL
dotsecrets-0.4.1.dist-info/entry_points.txt
dotsecrets-0.4.1.dist-info/top_level.txt
dotsecrets-0.4.1.dist-info/RECORD
