Metadata-Version: 2.1
Name: dotsecrets
Version: 0.4.1
Summary: DotSecrets is a tool to facilitate storing your dotfiles in Git, including those with private information. The private information is filtered before committing to the repository. DotSecrets is able to symlink your dotfiles into your home directory similar to Stow.
Home-page: https://github.com/oohlaf/dotsecrets
Author: Olaf Conradi
Author-email: olaf@conradi.org
License: BSD
Project-URL: Bug Reports, https://github.com/oohlaf/dotsecrets/issues
Keywords: manage dotfiles git stow secret private password
Classifier: License :: OSI Approved :: BSD License
Classifier: Development Status :: 4 - Beta
Classifier: Environment :: Console
Classifier: Intended Audience :: End Users/Desktop
Classifier: Topic :: System :: Shells
Classifier: Operating System :: POSIX
Classifier: Programming Language :: Python :: 3
Classifier: Programming Language :: Python :: 3.5
Classifier: Programming Language :: Python :: 3.6
Classifier: Programming Language :: Python :: 3.7
Classifier: Programming Language :: Python :: 3.8
Classifier: Programming Language :: Python :: 3.9
Classifier: Programming Language :: Python :: 3.10
Classifier: Programming Language :: Python :: 3.11
Classifier: Topic :: Software Development :: Version Control
Classifier: Topic :: System :: Systems Administration
Classifier: Topic :: Utilities
Requires-Python: >=3.5
Requires-Dist: ruamel.yaml (>=0.15.100)
Requires-Dist: dploy (>=0.1.2)
